recnn/__init__.py
recnn/optim.py
recnn/data/__init__.py
recnn/data/env.py
recnn/data/utils.py
recnn/nn/__init__.py
recnn/nn/algo.py
recnn/nn/models.py
recnn/nn/update.py
recnn/rep/TCN.py
recnn/rep/__init__.py
recnn/utils/__init__.py
recnn/utils/misc.py
recnn/utils/plot.py
recnn-0.1.dist-info/LICENSE
recnn-0.1.dist-info/METADATA
recnn-0.1.dist-info/WHEEL
recnn-0.1.dist-info/top_level.txt
recnn-0.1.dist-info/RECORD
