Metadata-Version: 2.1
Name: recnn
Version: 0.1
Summary: A Python toolkit for Reinforced News Recommendation.
Home-page: UNKNOWN
Author: Mike Watts
Author-email: awarebayes@gmail.com
License: Apache 2.0
Platform: UNKNOWN
Requires-Dist: torch
Requires-Dist: numpy
Requires-Dist: torchvision
